LICENSE.txt
MANIFEST.in
README.md
setup.cfg
setup.py
version.txt
buttersink/BestDiffs.py
buttersink/Butter.py
buttersink/ButterStore.py
buttersink/S3Store.py
buttersink/SSHStore.py
buttersink/Store.py
buttersink/__init__.py
buttersink/btrfs.py
buttersink/btrfslist.py
buttersink/buttersink.py
buttersink/ioctl.py
buttersink/version.txt
buttersink.egg-info/PKG-INFO
buttersink.egg-info/SOURCES.txt
buttersink.egg-info/dependency_links.txt
buttersink.egg-info/entry_points.txt
buttersink.egg-info/requires.txt
buttersink.egg-info/top_level.txt
scripts/checksumdir