Metadata-Version: 1.0
Name: buttersink
Version: 0.4
Summary: Buttersink is like rsync for btrfs snapshots
Home-page: https://github.com/AmesCornish/buttersink/wiki
Author: Ames Cornish
Author-email: buttersink@montebellopartners.com
License: GPLv3
Keywords: btrfs sync synchronize rsync snapshot subvolume buttersink backup
Platform: UNKNOWN
